{
  "ok": true,
  "source_chat": {
    "chat_id": null,
    "title": null,
    "type": null,
    "status": null,
    "file": "data/invite_volgograd_target_20260314_110900Z/round3_merged_still_missing.txt",
    "total_ids_in_source_file": 688
  },
  "target_chat": {
    "chat_id": -71879785613319,
    "title": "Авторынок | Волгоград",
    "type": "chat",
    "status": "active",
    "before_participants_count": 4930,
    "after_participants_count": 4945
  },
  "bot": {
    "user_id": 209468578,
    "name": "Beautera",
    "username": "id613002203036_bot"
  },
  "bot_membership_in_target": {
    "status": 200,
    "data": {
      "members": [
        {
          "last_access_time": 0,
          "is_owner": false,
          "is_admin": true,
          "join_time": 1773242984958,
          "permissions": [
            "can_call",
            "add_remove_members",
            "change_chat_info"
          ],
          "user_id": 209468578,
          "first_name": "Beautera",
          "username": "id613002203036_bot",
          "is_bot": true,
          "last_activity_time": 1773490108756,
          "description": "Оформление заказов \n",
          "avatar_url": "https://i.oneme.ru/i?r=BTFjO43w8Yr1OSJ4tcurq5HiY1X5djLJ9iN4Yni7aZa9LGvGPdxS9sOWIqUW770RGt0",
          "full_avatar_url": "https://i.oneme.ru/i?r=BTFjO43w8Yr1OSJ4tcurq5HiuOImY5yUOE2dMD0GUkmAvWvGPdxS9sOWIqUW770RGt0",
          "name": "Beautera"
        }
      ]
    }
  },
  "source_slice": {
    "start_index_0_based": 0,
    "end_index_exclusive_0_based": 400,
    "range_human": "1-400",
    "requested_count": 400,
    "selected_count": 400,
    "run_to_end": false,
    "skipped_bot_self_count": 0,
    "processed_count": 400,
    "invite_batch_size": 10
  },
  "run_options": {
    "dry_run": false,
    "invite_batch_size": 10,
    "pause_ms": 4200,
    "pause_jitter_ms": 200,
    "safe_min_pause_per_user_ms": 220,
    "max_retries": 1,
    "retry_delay_ms": 1200,
    "retry_backoff": 2,
    "retry_action_failed": false,
    "split_action_failed_batch": false,
    "stop_on_consecutive_action_failed": 0,
    "run_to_end": false,
    "wave_active_ms": 180000,
    "wave_rest_ms": 60000,
    "skip_existing_scan": false,
    "verify_chunk_size": 100,
    "verify_pause_ms": 80
  },
  "precheck": {
    "target_snapshot_pages": 50,
    "target_snapshot_members_count": 4930
  },
  "stop_triggered": null,
  "already_in_target_count": 0,
  "attempted_invite_count": 400,
  "invited_without_immediate_failure_count": 70,
  "verified_added_count": 23,
  "still_not_in_target_from_attempted_count": 377,
  "not_attempted_due_to_stop_count": 0,
  "still_not_in_target_from_this_chunk_count": 377,
  "failed_by_code": {
    "action_failed": 330
  },
  "failed_by_status": {
    "200": 330
  },
  "verification_errors_count": 0,
  "verification_errors_sample": [],
  "sample_verified_added_ids": [
    12071263,
    12074575,
    12094166,
    12125652,
    12137968,
    12155349,
    12185222,
    12192398,
    12197385,
    12233321,
    25878072,
    25881657,
    25885361,
    25895426,
    25900330,
    25904133,
    25940586,
    25944960,
    25945954,
    25993915,
    39495220,
    51736189,
    59767789
  ],
  "sample_still_missing_ids": [
    3404808,
    3527798,
    3605187,
    4191442,
    4648372,
    4720649,
    5224067,
    5437720,
    5513137,
    5794758,
    6419347,
    6675678,
    6802201,
    7259621,
    7356026,
    7481373,
    7483674,
    7586717,
    7716087,
    7927648,
    7948323,
    8146439,
    8273288,
    8342343,
    8409825,
    8950555,
    10581833,
    11109390,
    11238818,
    11377981,
    11396594,
    11456786,
    11643508,
    11698857,
    11803696,
    11862898,
    12033720,
    12280813,
    12309195,
    12440616,
    12476841,
    12529704,
    12573376,
    12733579,
    12763922,
    12801059,
    12827542,
    13160356,
    13506207,
    13868094
  ],
  "failed_details_sample": [
    {
      "user_id": 3404808,
      "attempts": 1,
      "status": 200,
      "code": "action_failed",
      "message": "API returned success=false"
    },
    {
      "user_id": 3527798,
      "attempts": 1,
      "status": 200,
      "code": "action_failed",
      "message": "API returned success=false"
    },
    {
      "user_id": 3605187,
      "attempts": 1,
      "status": 200,
      "code": "action_failed",
      "message": "API returned success=false"
    },
    {
      "user_id": 4191442,
      "attempts": 1,
      "status": 200,
      "code": "action_failed",
      "message": "API returned success=false"
    },
    {
      "user_id": 4648372,
      "attempts": 1,
      "status": 200,
      "code": "action_failed",
      "message": "API returned success=false"
    },
    {
      "user_id": 4720649,
      "attempts": 1,
      "status": 200,
      "code": "action_failed",
      "message": "API returned success=false"
    },
    {
      "user_id": 5224067,
      "attempts": 1,
      "status": 200,
      "code": "action_failed",
      "message": "API returned success=false"
    },
    {
      "user_id": 5437720,
      "attempts": 1,
      "status": 200,
      "code": "action_failed",
      "message": "API returned success=false"
    },
    {
      "user_id": 5513137,
      "attempts": 1,
      "status": 200,
      "code": "action_failed",
      "message": "API returned success=false"
    },
    {
      "user_id": 5794758,
      "attempts": 1,
      "status": 200,
      "code": "action_failed",
      "message": "API returned success=false"
    },
    {
      "user_id": 6419347,
      "attempts": 1,
      "status": 200,
      "code": "action_failed",
      "message": "API returned success=false"
    },
    {
      "user_id": 6675678,
      "attempts": 1,
      "status": 200,
      "code": "action_failed",
      "message": "API returned success=false"
    },
    {
      "user_id": 6802201,
      "attempts": 1,
      "status": 200,
      "code": "action_failed",
      "message": "API returned success=false"
    },
    {
      "user_id": 7259621,
      "attempts": 1,
      "status": 200,
      "code": "action_failed",
      "message": "API returned success=false"
    },
    {
      "user_id": 7356026,
      "attempts": 1,
      "status": 200,
      "code": "action_failed",
      "message": "API returned success=false"
    },
    {
      "user_id": 7481373,
      "attempts": 1,
      "status": 200,
      "code": "action_failed",
      "message": "API returned success=false"
    },
    {
      "user_id": 7483674,
      "attempts": 1,
      "status": 200,
      "code": "action_failed",
      "message": "API returned success=false"
    },
    {
      "user_id": 7586717,
      "attempts": 1,
      "status": 200,
      "code": "action_failed",
      "message": "API returned success=false"
    },
    {
      "user_id": 7716087,
      "attempts": 1,
      "status": 200,
      "code": "action_failed",
      "message": "API returned success=false"
    },
    {
      "user_id": 7927648,
      "attempts": 1,
      "status": 200,
      "code": "action_failed",
      "message": "API returned success=false"
    },
    {
      "user_id": 7948323,
      "attempts": 1,
      "status": 200,
      "code": "action_failed",
      "message": "API returned success=false"
    },
    {
      "user_id": 8146439,
      "attempts": 1,
      "status": 200,
      "code": "action_failed",
      "message": "API returned success=false"
    },
    {
      "user_id": 8273288,
      "attempts": 1,
      "status": 200,
      "code": "action_failed",
      "message": "API returned success=false"
    },
    {
      "user_id": 8342343,
      "attempts": 1,
      "status": 200,
      "code": "action_failed",
      "message": "API returned success=false"
    },
    {
      "user_id": 8409825,
      "attempts": 1,
      "status": 200,
      "code": "action_failed",
      "message": "API returned success=false"
    },
    {
      "user_id": 8950555,
      "attempts": 1,
      "status": 200,
      "code": "action_failed",
      "message": "API returned success=false"
    },
    {
      "user_id": 10581833,
      "attempts": 1,
      "status": 200,
      "code": "action_failed",
      "message": "API returned success=false"
    },
    {
      "user_id": 11109390,
      "attempts": 1,
      "status": 200,
      "code": "action_failed",
      "message": "API returned success=false"
    },
    {
      "user_id": 11238818,
      "attempts": 1,
      "status": 200,
      "code": "action_failed",
      "message": "API returned success=false"
    },
    {
      "user_id": 11377981,
      "attempts": 1,
      "status": 200,
      "code": "action_failed",
      "message": "API returned success=false"
    },
    {
      "user_id": 12476841,
      "attempts": 1,
      "status": 200,
      "code": "action_failed",
      "message": "API returned success=false"
    },
    {
      "user_id": 12529704,
      "attempts": 1,
      "status": 200,
      "code": "action_failed",
      "message": "API returned success=false"
    },
    {
      "user_id": 12573376,
      "attempts": 1,
      "status": 200,
      "code": "action_failed",
      "message": "API returned success=false"
    },
    {
      "user_id": 12733579,
      "attempts": 1,
      "status": 200,
      "code": "action_failed",
      "message": "API returned success=false"
    },
    {
      "user_id": 12763922,
      "attempts": 1,
      "status": 200,
      "code": "action_failed",
      "message": "API returned success=false"
    },
    {
      "user_id": 12801059,
      "attempts": 1,
      "status": 200,
      "code": "action_failed",
      "message": "API returned success=false"
    },
    {
      "user_id": 12827542,
      "attempts": 1,
      "status": 200,
      "code": "action_failed",
      "message": "API returned success=false"
    },
    {
      "user_id": 13160356,
      "attempts": 1,
      "status": 200,
      "code": "action_failed",
      "message": "API returned success=false"
    },
    {
      "user_id": 13506207,
      "attempts": 1,
      "status": 200,
      "code": "action_failed",
      "message": "API returned success=false"
    },
    {
      "user_id": 13868094,
      "attempts": 1,
      "status": 200,
      "code": "action_failed",
      "message": "API returned success=false"
    },
    {
      "user_id": 14787544,
      "attempts": 1,
      "status": 200,
      "code": "action_failed",
      "message": "API returned success=false"
    },
    {
      "user_id": 15098028,
      "attempts": 1,
      "status": 200,
      "code": "action_failed",
      "message": "API returned success=false"
    },
    {
      "user_id": 15301809,
      "attempts": 1,
      "status": 200,
      "code": "action_failed",
      "message": "API returned success=false"
    },
    {
      "user_id": 15782552,
      "attempts": 1,
      "status": 200,
      "code": "action_failed",
      "message": "API returned success=false"
    },
    {
      "user_id": 16078345,
      "attempts": 1,
      "status": 200,
      "code": "action_failed",
      "message": "API returned success=false"
    },
    {
      "user_id": 16256781,
      "attempts": 1,
      "status": 200,
      "code": "action_failed",
      "message": "API returned success=false"
    },
    {
      "user_id": 16267579,
      "attempts": 1,
      "status": 200,
      "code": "action_failed",
      "message": "API returned success=false"
    },
    {
      "user_id": 16631701,
      "attempts": 1,
      "status": 200,
      "code": "action_failed",
      "message": "API returned success=false"
    },
    {
      "user_id": 16851286,
      "attempts": 1,
      "status": 200,
      "code": "action_failed",
      "message": "API returned success=false"
    },
    {
      "user_id": 16891323,
      "attempts": 1,
      "status": 200,
      "code": "action_failed",
      "message": "API returned success=false"
    },
    {
      "user_id": 16956271,
      "attempts": 1,
      "status": 200,
      "code": "action_failed",
      "message": "API returned success=false"
    },
    {
      "user_id": 17019402,
      "attempts": 1,
      "status": 200,
      "code": "action_failed",
      "message": "API returned success=false"
    },
    {
      "user_id": 17038513,
      "attempts": 1,
      "status": 200,
      "code": "action_failed",
      "message": "API returned success=false"
    },
    {
      "user_id": 17381784,
      "attempts": 1,
      "status": 200,
      "code": "action_failed",
      "message": "API returned success=false"
    },
    {
      "user_id": 17402909,
      "attempts": 1,
      "status": 200,
      "code": "action_failed",
      "message": "API returned success=false"
    },
    {
      "user_id": 17453369,
      "attempts": 1,
      "status": 200,
      "code": "action_failed",
      "message": "API returned success=false"
    },
    {
      "user_id": 17488982,
      "attempts": 1,
      "status": 200,
      "code": "action_failed",
      "message": "API returned success=false"
    },
    {
      "user_id": 17951391,
      "attempts": 1,
      "status": 200,
      "code": "action_failed",
      "message": "API returned success=false"
    },
    {
      "user_id": 18088124,
      "attempts": 1,
      "status": 200,
      "code": "action_failed",
      "message": "API returned success=false"
    },
    {
      "user_id": 18515856,
      "attempts": 1,
      "status": 200,
      "code": "action_failed",
      "message": "API returned success=false"
    },
    {
      "user_id": 18564986,
      "attempts": 1,
      "status": 200,
      "code": "action_failed",
      "message": "API returned success=false"
    },
    {
      "user_id": 18593271,
      "attempts": 1,
      "status": 200,
      "code": "action_failed",
      "message": "API returned success=false"
    },
    {
      "user_id": 18707715,
      "attempts": 1,
      "status": 200,
      "code": "action_failed",
      "message": "API returned success=false"
    },
    {
      "user_id": 18894830,
      "attempts": 1,
      "status": 200,
      "code": "action_failed",
      "message": "API returned success=false"
    },
    {
      "user_id": 19038160,
      "attempts": 1,
      "status": 200,
      "code": "action_failed",
      "message": "API returned success=false"
    },
    {
      "user_id": 19146184,
      "attempts": 1,
      "status": 200,
      "code": "action_failed",
      "message": "API returned success=false"
    },
    {
      "user_id": 19285240,
      "attempts": 1,
      "status": 200,
      "code": "action_failed",
      "message": "API returned success=false"
    },
    {
      "user_id": 19463644,
      "attempts": 1,
      "status": 200,
      "code": "action_failed",
      "message": "API returned success=false"
    },
    {
      "user_id": 19463829,
      "attempts": 1,
      "status": 200,
      "code": "action_failed",
      "message": "API returned success=false"
    },
    {
      "user_id": 19496163,
      "attempts": 1,
      "status": 200,
      "code": "action_failed",
      "message": "API returned success=false"
    },
    {
      "user_id": 19649146,
      "attempts": 1,
      "status": 200,
      "code": "action_failed",
      "message": "API returned success=false"
    },
    {
      "user_id": 19835643,
      "attempts": 1,
      "status": 200,
      "code": "action_failed",
      "message": "API returned success=false"
    },
    {
      "user_id": 19856241,
      "attempts": 1,
      "status": 200,
      "code": "action_failed",
      "message": "API returned success=false"
    },
    {
      "user_id": 19876078,
      "attempts": 1,
      "status": 200,
      "code": "action_failed",
      "message": "API returned success=false"
    },
    {
      "user_id": 20213700,
      "attempts": 1,
      "status": 200,
      "code": "action_failed",
      "message": "API returned success=false"
    },
    {
      "user_id": 20321969,
      "attempts": 1,
      "status": 200,
      "code": "action_failed",
      "message": "API returned success=false"
    },
    {
      "user_id": 20728402,
      "attempts": 1,
      "status": 200,
      "code": "action_failed",
      "message": "API returned success=false"
    },
    {
      "user_id": 20782640,
      "attempts": 1,
      "status": 200,
      "code": "action_failed",
      "message": "API returned success=false"
    },
    {
      "user_id": 20880462,
      "attempts": 1,
      "status": 200,
      "code": "action_failed",
      "message": "API returned success=false"
    },
    {
      "user_id": 20903822,
      "attempts": 1,
      "status": 200,
      "code": "action_failed",
      "message": "API returned success=false"
    },
    {
      "user_id": 21005203,
      "attempts": 1,
      "status": 200,
      "code": "action_failed",
      "message": "API returned success=false"
    },
    {
      "user_id": 21295987,
      "attempts": 1,
      "status": 200,
      "code": "action_failed",
      "message": "API returned success=false"
    },
    {
      "user_id": 21313480,
      "attempts": 1,
      "status": 200,
      "code": "action_failed",
      "message": "API returned success=false"
    },
    {
      "user_id": 21438752,
      "attempts": 1,
      "status": 200,
      "code": "action_failed",
      "message": "API returned success=false"
    },
    {
      "user_id": 21456323,
      "attempts": 1,
      "status": 200,
      "code": "action_failed",
      "message": "API returned success=false"
    },
    {
      "user_id": 21494149,
      "attempts": 1,
      "status": 200,
      "code": "action_failed",
      "message": "API returned success=false"
    },
    {
      "user_id": 21518467,
      "attempts": 1,
      "status": 200,
      "code": "action_failed",
      "message": "API returned success=false"
    },
    {
      "user_id": 21555173,
      "attempts": 1,
      "status": 200,
      "code": "action_failed",
      "message": "API returned success=false"
    },
    {
      "user_id": 21576053,
      "attempts": 1,
      "status": 200,
      "code": "action_failed",
      "message": "API returned success=false"
    },
    {
      "user_id": 21627011,
      "attempts": 1,
      "status": 200,
      "code": "action_failed",
      "message": "API returned success=false"
    },
    {
      "user_id": 21667699,
      "attempts": 1,
      "status": 200,
      "code": "action_failed",
      "message": "API returned success=false"
    },
    {
      "user_id": 21717149,
      "attempts": 1,
      "status": 200,
      "code": "action_failed",
      "message": "API returned success=false"
    },
    {
      "user_id": 21784806,
      "attempts": 1,
      "status": 200,
      "code": "action_failed",
      "message": "API returned success=false"
    },
    {
      "user_id": 22026915,
      "attempts": 1,
      "status": 200,
      "code": "action_failed",
      "message": "API returned success=false"
    },
    {
      "user_id": 22098873,
      "attempts": 1,
      "status": 200,
      "code": "action_failed",
      "message": "API returned success=false"
    },
    {
      "user_id": 22202695,
      "attempts": 1,
      "status": 200,
      "code": "action_failed",
      "message": "API returned success=false"
    },
    {
      "user_id": 22281858,
      "attempts": 1,
      "status": 200,
      "code": "action_failed",
      "message": "API returned success=false"
    },
    {
      "user_id": 22341851,
      "attempts": 1,
      "status": 200,
      "code": "action_failed",
      "message": "API returned success=false"
    },
    {
      "user_id": 22406264,
      "attempts": 1,
      "status": 200,
      "code": "action_failed",
      "message": "API returned success=false"
    },
    {
      "user_id": 22434579,
      "attempts": 1,
      "status": 200,
      "code": "action_failed",
      "message": "API returned success=false"
    },
    {
      "user_id": 22482306,
      "attempts": 1,
      "status": 200,
      "code": "action_failed",
      "message": "API returned success=false"
    },
    {
      "user_id": 22494607,
      "attempts": 1,
      "status": 200,
      "code": "action_failed",
      "message": "API returned success=false"
    },
    {
      "user_id": 22535743,
      "attempts": 1,
      "status": 200,
      "code": "action_failed",
      "message": "API returned success=false"
    },
    {
      "user_id": 22624772,
      "attempts": 1,
      "status": 200,
      "code": "action_failed",
      "message": "API returned success=false"
    },
    {
      "user_id": 22749282,
      "attempts": 1,
      "status": 200,
      "code": "action_failed",
      "message": "API returned success=false"
    },
    {
      "user_id": 22775775,
      "attempts": 1,
      "status": 200,
      "code": "action_failed",
      "message": "API returned success=false"
    },
    {
      "user_id": 22871299,
      "attempts": 1,
      "status": 200,
      "code": "action_failed",
      "message": "API returned success=false"
    },
    {
      "user_id": 22887194,
      "attempts": 1,
      "status": 200,
      "code": "action_failed",
      "message": "API returned success=false"
    },
    {
      "user_id": 22917222,
      "attempts": 1,
      "status": 200,
      "code": "action_failed",
      "message": "API returned success=false"
    },
    {
      "user_id": 23092587,
      "attempts": 1,
      "status": 200,
      "code": "action_failed",
      "message": "API returned success=false"
    },
    {
      "user_id": 23140961,
      "attempts": 1,
      "status": 200,
      "code": "action_failed",
      "message": "API returned success=false"
    },
    {
      "user_id": 23271074,
      "attempts": 1,
      "status": 200,
      "code": "action_failed",
      "message": "API returned success=false"
    },
    {
      "user_id": 23370219,
      "attempts": 1,
      "status": 200,
      "code": "action_failed",
      "message": "API returned success=false"
    },
    {
      "user_id": 23386768,
      "attempts": 1,
      "status": 200,
      "code": "action_failed",
      "message": "API returned success=false"
    },
    {
      "user_id": 23400288,
      "attempts": 1,
      "status": 200,
      "code": "action_failed",
      "message": "API returned success=false"
    },
    {
      "user_id": 23411183,
      "attempts": 1,
      "status": 200,
      "code": "action_failed",
      "message": "API returned success=false"
    },
    {
      "user_id": 24008241,
      "attempts": 1,
      "status": 200,
      "code": "action_failed",
      "message": "API returned success=false"
    },
    {
      "user_id": 24178063,
      "attempts": 1,
      "status": 200,
      "code": "action_failed",
      "message": "API returned success=false"
    },
    {
      "user_id": 24211779,
      "attempts": 1,
      "status": 200,
      "code": "action_failed",
      "message": "API returned success=false"
    },
    {
      "user_id": 24402388,
      "attempts": 1,
      "status": 200,
      "code": "action_failed",
      "message": "API returned success=false"
    },
    {
      "user_id": 24520433,
      "attempts": 1,
      "status": 200,
      "code": "action_failed",
      "message": "API returned success=false"
    },
    {
      "user_id": 24671591,
      "attempts": 1,
      "status": 200,
      "code": "action_failed",
      "message": "API returned success=false"
    },
    {
      "user_id": 24691121,
      "attempts": 1,
      "status": 200,
      "code": "action_failed",
      "message": "API returned success=false"
    },
    {
      "user_id": 24917434,
      "attempts": 1,
      "status": 200,
      "code": "action_failed",
      "message": "API returned success=false"
    },
    {
      "user_id": 25214749,
      "attempts": 1,
      "status": 200,
      "code": "action_failed",
      "message": "API returned success=false"
    },
    {
      "user_id": 25216795,
      "attempts": 1,
      "status": 200,
      "code": "action_failed",
      "message": "API returned success=false"
    },
    {
      "user_id": 25570372,
      "attempts": 1,
      "status": 200,
      "code": "action_failed",
      "message": "API returned success=false"
    },
    {
      "user_id": 25578882,
      "attempts": 1,
      "status": 200,
      "code": "action_failed",
      "message": "API returned success=false"
    },
    {
      "user_id": 25615101,
      "attempts": 1,
      "status": 200,
      "code": "action_failed",
      "message": "API returned success=false"
    },
    {
      "user_id": 25693162,
      "attempts": 1,
      "status": 200,
      "code": "action_failed",
      "message": "API returned success=false"
    },
    {
      "user_id": 26698051,
      "attempts": 1,
      "status": 200,
      "code": "action_failed",
      "message": "API returned success=false"
    },
    {
      "user_id": 26704690,
      "attempts": 1,
      "status": 200,
      "code": "action_failed",
      "message": "API returned success=false"
    },
    {
      "user_id": 26745306,
      "attempts": 1,
      "status": 200,
      "code": "action_failed",
      "message": "API returned success=false"
    },
    {
      "user_id": 26794195,
      "attempts": 1,
      "status": 200,
      "code": "action_failed",
      "message": "API returned success=false"
    },
    {
      "user_id": 26800577,
      "attempts": 1,
      "status": 200,
      "code": "action_failed",
      "message": "API returned success=false"
    },
    {
      "user_id": 26813783,
      "attempts": 1,
      "status": 200,
      "code": "action_failed",
      "message": "API returned success=false"
    },
    {
      "user_id": 27012493,
      "attempts": 1,
      "status": 200,
      "code": "action_failed",
      "message": "API returned success=false"
    },
    {
      "user_id": 27050954,
      "attempts": 1,
      "status": 200,
      "code": "action_failed",
      "message": "API returned success=false"
    },
    {
      "user_id": 27138071,
      "attempts": 1,
      "status": 200,
      "code": "action_failed",
      "message": "API returned success=false"
    },
    {
      "user_id": 27204423,
      "attempts": 1,
      "status": 200,
      "code": "action_failed",
      "message": "API returned success=false"
    },
    {
      "user_id": 27695426,
      "attempts": 1,
      "status": 200,
      "code": "action_failed",
      "message": "API returned success=false"
    },
    {
      "user_id": 27790337,
      "attempts": 1,
      "status": 200,
      "code": "action_failed",
      "message": "API returned success=false"
    },
    {
      "user_id": 27877580,
      "attempts": 1,
      "status": 200,
      "code": "action_failed",
      "message": "API returned success=false"
    },
    {
      "user_id": 28011974,
      "attempts": 1,
      "status": 200,
      "code": "action_failed",
      "message": "API returned success=false"
    },
    {
      "user_id": 28187309,
      "attempts": 1,
      "status": 200,
      "code": "action_failed",
      "message": "API returned success=false"
    },
    {
      "user_id": 28260770,
      "attempts": 1,
      "status": 200,
      "code": "action_failed",
      "message": "API returned success=false"
    },
    {
      "user_id": 28350012,
      "attempts": 1,
      "status": 200,
      "code": "action_failed",
      "message": "API returned success=false"
    },
    {
      "user_id": 28476359,
      "attempts": 1,
      "status": 200,
      "code": "action_failed",
      "message": "API returned success=false"
    },
    {
      "user_id": 28677722,
      "attempts": 1,
      "status": 200,
      "code": "action_failed",
      "message": "API returned success=false"
    },
    {
      "user_id": 28786394,
      "attempts": 1,
      "status": 200,
      "code": "action_failed",
      "message": "API returned success=false"
    },
    {
      "user_id": 28846017,
      "attempts": 1,
      "status": 200,
      "code": "action_failed",
      "message": "API returned success=false"
    },
    {
      "user_id": 29005900,
      "attempts": 1,
      "status": 200,
      "code": "action_failed",
      "message": "API returned success=false"
    },
    {
      "user_id": 29040475,
      "attempts": 1,
      "status": 200,
      "code": "action_failed",
      "message": "API returned success=false"
    },
    {
      "user_id": 29063355,
      "attempts": 1,
      "status": 200,
      "code": "action_failed",
      "message": "API returned success=false"
    },
    {
      "user_id": 29219535,
      "attempts": 1,
      "status": 200,
      "code": "action_failed",
      "message": "API returned success=false"
    },
    {
      "user_id": 29551044,
      "attempts": 1,
      "status": 200,
      "code": "action_failed",
      "message": "API returned success=false"
    },
    {
      "user_id": 29635114,
      "attempts": 1,
      "status": 200,
      "code": "action_failed",
      "message": "API returned success=false"
    },
    {
      "user_id": 29821034,
      "attempts": 1,
      "status": 200,
      "code": "action_failed",
      "message": "API returned success=false"
    },
    {
      "user_id": 29891868,
      "attempts": 1,
      "status": 200,
      "code": "action_failed",
      "message": "API returned success=false"
    },
    {
      "user_id": 29978118,
      "attempts": 1,
      "status": 200,
      "code": "action_failed",
      "message": "API returned success=false"
    },
    {
      "user_id": 30037935,
      "attempts": 1,
      "status": 200,
      "code": "action_failed",
      "message": "API returned success=false"
    },
    {
      "user_id": 30052526,
      "attempts": 1,
      "status": 200,
      "code": "action_failed",
      "message": "API returned success=false"
    },
    {
      "user_id": 30265689,
      "attempts": 1,
      "status": 200,
      "code": "action_failed",
      "message": "API returned success=false"
    },
    {
      "user_id": 30292612,
      "attempts": 1,
      "status": 200,
      "code": "action_failed",
      "message": "API returned success=false"
    },
    {
      "user_id": 30437273,
      "attempts": 1,
      "status": 200,
      "code": "action_failed",
      "message": "API returned success=false"
    },
    {
      "user_id": 30713062,
      "attempts": 1,
      "status": 200,
      "code": "action_failed",
      "message": "API returned success=false"
    },
    {
      "user_id": 30757862,
      "attempts": 1,
      "status": 200,
      "code": "action_failed",
      "message": "API returned success=false"
    },
    {
      "user_id": 30856611,
      "attempts": 1,
      "status": 200,
      "code": "action_failed",
      "message": "API returned success=false"
    },
    {
      "user_id": 30865238,
      "attempts": 1,
      "status": 200,
      "code": "action_failed",
      "message": "API returned success=false"
    },
    {
      "user_id": 30957875,
      "attempts": 1,
      "status": 200,
      "code": "action_failed",
      "message": "API returned success=false"
    },
    {
      "user_id": 31009865,
      "attempts": 1,
      "status": 200,
      "code": "action_failed",
      "message": "API returned success=false"
    },
    {
      "user_id": 31065896,
      "attempts": 1,
      "status": 200,
      "code": "action_failed",
      "message": "API returned success=false"
    },
    {
      "user_id": 31085920,
      "attempts": 1,
      "status": 200,
      "code": "action_failed",
      "message": "API returned success=false"
    },
    {
      "user_id": 31297940,
      "attempts": 1,
      "status": 200,
      "code": "action_failed",
      "message": "API returned success=false"
    },
    {
      "user_id": 31640837,
      "attempts": 1,
      "status": 200,
      "code": "action_failed",
      "message": "API returned success=false"
    },
    {
      "user_id": 31665991,
      "attempts": 1,
      "status": 200,
      "code": "action_failed",
      "message": "API returned success=false"
    },
    {
      "user_id": 31687096,
      "attempts": 1,
      "status": 200,
      "code": "action_failed",
      "message": "API returned success=false"
    },
    {
      "user_id": 31797394,
      "attempts": 1,
      "status": 200,
      "code": "action_failed",
      "message": "API returned success=false"
    },
    {
      "user_id": 32075140,
      "attempts": 1,
      "status": 200,
      "code": "action_failed",
      "message": "API returned success=false"
    },
    {
      "user_id": 32122904,
      "attempts": 1,
      "status": 200,
      "code": "action_failed",
      "message": "API returned success=false"
    },
    {
      "user_id": 32129890,
      "attempts": 1,
      "status": 200,
      "code": "action_failed",
      "message": "API returned success=false"
    },
    {
      "user_id": 32613249,
      "attempts": 1,
      "status": 200,
      "code": "action_failed",
      "message": "API returned success=false"
    },
    {
      "user_id": 32905598,
      "attempts": 1,
      "status": 200,
      "code": "action_failed",
      "message": "API returned success=false"
    },
    {
      "user_id": 33064194,
      "attempts": 1,
      "status": 200,
      "code": "action_failed",
      "message": "API returned success=false"
    },
    {
      "user_id": 33076637,
      "attempts": 1,
      "status": 200,
      "code": "action_failed",
      "message": "API returned success=false"
    },
    {
      "user_id": 33138012,
      "attempts": 1,
      "status": 200,
      "code": "action_failed",
      "message": "API returned success=false"
    },
    {
      "user_id": 33394593,
      "attempts": 1,
      "status": 200,
      "code": "action_failed",
      "message": "API returned success=false"
    },
    {
      "user_id": 33727888,
      "attempts": 1,
      "status": 200,
      "code": "action_failed",
      "message": "API returned success=false"
    },
    {
      "user_id": 33796645,
      "attempts": 1,
      "status": 200,
      "code": "action_failed",
      "message": "API returned success=false"
    },
    {
      "user_id": 34184512,
      "attempts": 1,
      "status": 200,
      "code": "action_failed",
      "message": "API returned success=false"
    },
    {
      "user_id": 34502618,
      "attempts": 1,
      "status": 200,
      "code": "action_failed",
      "message": "API returned success=false"
    },
    {
      "user_id": 34688525,
      "attempts": 1,
      "status": 200,
      "code": "action_failed",
      "message": "API returned success=false"
    },
    {
      "user_id": 34875820,
      "attempts": 1,
      "status": 200,
      "code": "action_failed",
      "message": "API returned success=false"
    },
    {
      "user_id": 34914542,
      "attempts": 1,
      "status": 200,
      "code": "action_failed",
      "message": "API returned success=false"
    },
    {
      "user_id": 34936583,
      "attempts": 1,
      "status": 200,
      "code": "action_failed",
      "message": "API returned success=false"
    },
    {
      "user_id": 35417702,
      "attempts": 1,
      "status": 200,
      "code": "action_failed",
      "message": "API returned success=false"
    },
    {
      "user_id": 35753654,
      "attempts": 1,
      "status": 200,
      "code": "action_failed",
      "message": "API returned success=false"
    },
    {
      "user_id": 35845974,
      "attempts": 1,
      "status": 200,
      "code": "action_failed",
      "message": "API returned success=false"
    },
    {
      "user_id": 35956977,
      "attempts": 1,
      "status": 200,
      "code": "action_failed",
      "message": "API returned success=false"
    },
    {
      "user_id": 36101036,
      "attempts": 1,
      "status": 200,
      "code": "action_failed",
      "message": "API returned success=false"
    }
  ],
  "generated_at_iso": "2026-03-14T12:12:12.447Z"
}
