{
  "ok": true,
  "source_chat": {
    "chat_id": null,
    "title": null,
    "type": null,
    "status": null,
    "file": "трупы",
    "total_ids_in_source_file": 20000
  },
  "target_chat": {
    "chat_id": -73652908047066,
    "title": "ХВАТАЙ БЕЗДЕП БОНУСЫ",
    "type": "chat",
    "status": "active",
    "before_participants_count": 2563,
    "after_participants_count": 2981
  },
  "bot": {
    "user_id": 269932414,
    "name": "Интелликс",
    "username": "id613070470872_bot"
  },
  "bot_membership_in_target": {
    "status": 200,
    "data": {
      "members": [
        {
          "last_access_time": 1776452516261,
          "is_owner": false,
          "is_admin": true,
          "join_time": 1776449741058,
          "permissions": [
            "change_chat_info",
            "pin_message",
            "add_remove_members",
            "can_call",
            "read_all_messages",
            "write"
          ],
          "user_id": 269932414,
          "first_name": "Интелликс",
          "username": "id613070470872_bot",
          "is_bot": true,
          "last_activity_time": 1776459311143,
          "description": "Интелликс — умный чат-бот для быстрых ответов, идей и помощи в повседневных задачах.",
          "avatar_url": "https://i.oneme.ru/i?r=BTFjO43w8Yr1OSJ4tcurq5Hi8qZRFpjsW-cdEBxfPSRmW34BN_hBExMnnFcFEy-tCzo",
          "full_avatar_url": "https://i.oneme.ru/i?r=BTFjO43w8Yr1OSJ4tcurq5Hi40nY5-QvEnF9U6GjKypVHH4BN_hBExMnnFcFEy-tCzo",
          "name": "Интелликс"
        }
      ]
    }
  },
  "source_slice": {
    "start_index_0_based": 4500,
    "end_index_exclusive_0_based": 5000,
    "range_human": "4501-5000",
    "requested_count": 500,
    "selected_count": 500,
    "skipped_bot_self_count": 0,
    "processed_count": 500,
    "invite_batch_size": 10
  },
  "run_options": {
    "dry_run": false,
    "invite_batch_size": 10,
    "pause_ms": 3000,
    "throttle_7m": false,
    "max_retries": 0,
    "retry_delay_ms": 1200,
    "retry_backoff": 2,
    "retry_action_failed": false,
    "split_action_failed_batch": false,
    "stop_on_consecutive_action_failed": 0,
    "skip_existing_scan": false,
    "verify_chunk_size": 100,
    "verify_pause_ms": 80
  },
  "precheck": {
    "target_snapshot_pages": 26,
    "target_snapshot_members_count": 2563
  },
  "stop_triggered": null,
  "already_in_target_count": 0,
  "attempted_invite_count": 500,
  "invited_without_immediate_failure_count": 500,
  "verified_added_count": 466,
  "still_not_in_target_from_attempted_count": 34,
  "not_attempted_due_to_stop_count": 0,
  "still_not_in_target_from_this_chunk_count": 34,
  "failed_by_code": {},
  "failed_by_status": {},
  "verification_errors_count": 0,
  "verification_errors_sample": [],
  "sample_verified_added_ids": [
    102522408,
    102459465,
    102435712,
    102179365,
    102084954,
    101666992,
    101192041,
    101046448,
    100994684,
    100879343,
    100846272,
    100760511,
    100699888,
    100411410,
    100212880,
    100159170,
    100114752,
    99769984,
    99468145,
    99322962,
    99258703,
    99223781,
    99198396,
    99046415,
    98759791,
    98570820,
    98253072,
    97856632,
    97783750,
    97697196,
    97495185,
    97410599,
    97320049,
    97252729,
    97148248,
    97120206,
    96925322,
    96877730,
    96799234,
    96779784,
    96765224,
    96743119,
    96673586,
    96630427,
    96505667,
    96283491,
    96203170,
    96147329,
    96072086,
    96039958
  ],
  "sample_still_missing_ids": [
    102058793,
    99767579,
    99369113,
    97736838,
    95787297,
    93566280,
    92245836,
    91321215,
    90125374,
    89739183,
    88407724,
    85328579,
    85237106,
    85158606,
    83606523,
    83264675,
    80566078,
    80340202,
    80327490,
    79876884,
    78809042,
    78434695,
    78358451,
    77723830,
    75068475,
    74370298,
    73825482,
    73222098,
    71942449,
    70830245,
    66599456,
    61686229,
    61013198,
    59280281
  ],
  "failed_details_sample": [],
  "generated_at_iso": "2026-04-17T20:58:06.392Z"
}
