{
  "ok": true,
  "source_chat": {
    "chat_id": -68236812389073,
    "title": "Авторынок Волгоградская область",
    "file": "data/avtorynok_volgogradskaya_oblast_member_ids.json"
  },
  "target_chat": {
    "chat_id": -71313986483690,
    "title": "Волгоград Объявления | Новости",
    "type": "chat",
    "before_participants_count": 1247,
    "after_participants_count": 1247
  },
  "bot_membership_in_target": {
    "status": 200,
    "data": {
      "members": [
        {
          "last_access_time": 0,
          "is_owner": false,
          "is_admin": false,
          "join_time": 1771963599418,
          "user_id": 210487679,
          "first_name": "Бот Менеджер",
          "username": "id613002203036_1_bot",
          "is_bot": true,
          "last_activity_time": 1771966474704,
          "description": "Бот Менеджер — инструмент для работы в чатах и каналах: модерация, автоответы, публикация постов, сбор заявок и управление участниками. Упрощает администрирование и экономит время 24/7.",
          "avatar_url": "https://i.oneme.ru/i?r=BTFjO43w8Yr1OSJ4tcurq5HiR7e3BI6D-gCWBjbI_OzwCTawY_4sp8NyqX5j2Jshwb0",
          "full_avatar_url": "https://i.oneme.ru/i?r=BTFjO43w8Yr1OSJ4tcurq5HiyQ03k3jxWqLAh7IU9_HtgDawY_4sp8NyqX5j2Jshwb0",
          "name": "Бот Менеджер"
        }
      ]
    }
  },
  "source_slice": {
    "start_index_0_based": 300,
    "end_index_exclusive_0_based": 600,
    "range_human": "301-600",
    "count": 300
  },
  "already_in_target_count": 13,
  "attempted_invite_count": 287,
  "invited_without_immediate_failure_count": 0,
  "verified_added_count": 0,
  "still_not_in_target_from_this_chunk_count": 287,
  "pause_ms": 180,
  "failed_by_code": {
    "action_failed": 287
  },
  "sample_verified_added_ids": [],
  "sample_still_missing_ids": [
    16114801,
    16136512,
    16178243,
    16204006,
    16261556,
    16267579,
    16276226,
    16297392,
    16348839,
    16350820,
    16356359,
    16365828,
    16376488,
    16378047,
    16378599,
    16418487,
    16480751,
    16495611,
    16508944,
    16561531,
    16574726,
    16604503,
    16618239,
    16631701,
    16661779,
    16668656,
    16702611,
    16703832,
    16737617,
    16761292,
    16767147,
    16785867,
    16812880,
    16843380,
    16844281,
    16868300,
    16925383,
    16934879,
    16955264,
    16971371,
    16991987,
    17019402,
    17075662,
    17103438,
    17132461,
    17132567,
    17146167,
    17153838,
    17225606,
    17257140
  ],
  "failed_details_sample": [
    {
      "user_id": 16114801,
      "status": 200,
      "code": "action_failed",
      "message": "API returned success=false"
    },
    {
      "user_id": 16136512,
      "status": 200,
      "code": "action_failed",
      "message": "API returned success=false"
    },
    {
      "user_id": 16178243,
      "status": 200,
      "code": "action_failed",
      "message": "API returned success=false"
    },
    {
      "user_id": 16204006,
      "status": 200,
      "code": "action_failed",
      "message": "API returned success=false"
    },
    {
      "user_id": 16261556,
      "status": 200,
      "code": "action_failed",
      "message": "API returned success=false"
    },
    {
      "user_id": 16267579,
      "status": 200,
      "code": "action_failed",
      "message": "API returned success=false"
    },
    {
      "user_id": 16276226,
      "status": 200,
      "code": "action_failed",
      "message": "API returned success=false"
    },
    {
      "user_id": 16297392,
      "status": 200,
      "code": "action_failed",
      "message": "API returned success=false"
    },
    {
      "user_id": 16348839,
      "status": 200,
      "code": "action_failed",
      "message": "API returned success=false"
    },
    {
      "user_id": 16350820,
      "status": 200,
      "code": "action_failed",
      "message": "API returned success=false"
    },
    {
      "user_id": 16356359,
      "status": 200,
      "code": "action_failed",
      "message": "API returned success=false"
    },
    {
      "user_id": 16365828,
      "status": 200,
      "code": "action_failed",
      "message": "API returned success=false"
    },
    {
      "user_id": 16376488,
      "status": 200,
      "code": "action_failed",
      "message": "API returned success=false"
    },
    {
      "user_id": 16378047,
      "status": 200,
      "code": "action_failed",
      "message": "API returned success=false"
    },
    {
      "user_id": 16378599,
      "status": 200,
      "code": "action_failed",
      "message": "API returned success=false"
    },
    {
      "user_id": 16418487,
      "status": 200,
      "code": "action_failed",
      "message": "API returned success=false"
    },
    {
      "user_id": 16480751,
      "status": 200,
      "code": "action_failed",
      "message": "API returned success=false"
    },
    {
      "user_id": 16495611,
      "status": 200,
      "code": "action_failed",
      "message": "API returned success=false"
    },
    {
      "user_id": 16508944,
      "status": 200,
      "code": "action_failed",
      "message": "API returned success=false"
    },
    {
      "user_id": 16561531,
      "status": 200,
      "code": "action_failed",
      "message": "API returned success=false"
    },
    {
      "user_id": 16574726,
      "status": 200,
      "code": "action_failed",
      "message": "API returned success=false"
    },
    {
      "user_id": 16604503,
      "status": 200,
      "code": "action_failed",
      "message": "API returned success=false"
    },
    {
      "user_id": 16618239,
      "status": 200,
      "code": "action_failed",
      "message": "API returned success=false"
    },
    {
      "user_id": 16631701,
      "status": 200,
      "code": "action_failed",
      "message": "API returned success=false"
    },
    {
      "user_id": 16661779,
      "status": 200,
      "code": "action_failed",
      "message": "API returned success=false"
    },
    {
      "user_id": 16668656,
      "status": 200,
      "code": "action_failed",
      "message": "API returned success=false"
    },
    {
      "user_id": 16702611,
      "status": 200,
      "code": "action_failed",
      "message": "API returned success=false"
    },
    {
      "user_id": 16703832,
      "status": 200,
      "code": "action_failed",
      "message": "API returned success=false"
    },
    {
      "user_id": 16737617,
      "status": 200,
      "code": "action_failed",
      "message": "API returned success=false"
    },
    {
      "user_id": 16761292,
      "status": 200,
      "code": "action_failed",
      "message": "API returned success=false"
    },
    {
      "user_id": 16767147,
      "status": 200,
      "code": "action_failed",
      "message": "API returned success=false"
    },
    {
      "user_id": 16785867,
      "status": 200,
      "code": "action_failed",
      "message": "API returned success=false"
    },
    {
      "user_id": 16812880,
      "status": 200,
      "code": "action_failed",
      "message": "API returned success=false"
    },
    {
      "user_id": 16843380,
      "status": 200,
      "code": "action_failed",
      "message": "API returned success=false"
    },
    {
      "user_id": 16844281,
      "status": 200,
      "code": "action_failed",
      "message": "API returned success=false"
    },
    {
      "user_id": 16868300,
      "status": 200,
      "code": "action_failed",
      "message": "API returned success=false"
    },
    {
      "user_id": 16925383,
      "status": 200,
      "code": "action_failed",
      "message": "API returned success=false"
    },
    {
      "user_id": 16934879,
      "status": 200,
      "code": "action_failed",
      "message": "API returned success=false"
    },
    {
      "user_id": 16955264,
      "status": 200,
      "code": "action_failed",
      "message": "API returned success=false"
    },
    {
      "user_id": 16971371,
      "status": 200,
      "code": "action_failed",
      "message": "API returned success=false"
    },
    {
      "user_id": 16991987,
      "status": 200,
      "code": "action_failed",
      "message": "API returned success=false"
    },
    {
      "user_id": 17019402,
      "status": 200,
      "code": "action_failed",
      "message": "API returned success=false"
    },
    {
      "user_id": 17075662,
      "status": 200,
      "code": "action_failed",
      "message": "API returned success=false"
    },
    {
      "user_id": 17103438,
      "status": 200,
      "code": "action_failed",
      "message": "API returned success=false"
    },
    {
      "user_id": 17132461,
      "status": 200,
      "code": "action_failed",
      "message": "API returned success=false"
    },
    {
      "user_id": 17132567,
      "status": 200,
      "code": "action_failed",
      "message": "API returned success=false"
    },
    {
      "user_id": 17146167,
      "status": 200,
      "code": "action_failed",
      "message": "API returned success=false"
    },
    {
      "user_id": 17153838,
      "status": 200,
      "code": "action_failed",
      "message": "API returned success=false"
    },
    {
      "user_id": 17225606,
      "status": 200,
      "code": "action_failed",
      "message": "API returned success=false"
    },
    {
      "user_id": 17257140,
      "status": 200,
      "code": "action_failed",
      "message": "API returned success=false"
    },
    {
      "user_id": 17260027,
      "status": 200,
      "code": "action_failed",
      "message": "API returned success=false"
    },
    {
      "user_id": 17264112,
      "status": 200,
      "code": "action_failed",
      "message": "API returned success=false"
    },
    {
      "user_id": 17270857,
      "status": 200,
      "code": "action_failed",
      "message": "API returned success=false"
    },
    {
      "user_id": 17279418,
      "status": 200,
      "code": "action_failed",
      "message": "API returned success=false"
    },
    {
      "user_id": 17286696,
      "status": 200,
      "code": "action_failed",
      "message": "API returned success=false"
    },
    {
      "user_id": 17338283,
      "status": 200,
      "code": "action_failed",
      "message": "API returned success=false"
    },
    {
      "user_id": 17359886,
      "status": 200,
      "code": "action_failed",
      "message": "API returned success=false"
    },
    {
      "user_id": 17365652,
      "status": 200,
      "code": "action_failed",
      "message": "API returned success=false"
    },
    {
      "user_id": 17377589,
      "status": 200,
      "code": "action_failed",
      "message": "API returned success=false"
    },
    {
      "user_id": 17381784,
      "status": 200,
      "code": "action_failed",
      "message": "API returned success=false"
    },
    {
      "user_id": 17382201,
      "status": 200,
      "code": "action_failed",
      "message": "API returned success=false"
    },
    {
      "user_id": 17387352,
      "status": 200,
      "code": "action_failed",
      "message": "API returned success=false"
    },
    {
      "user_id": 17408899,
      "status": 200,
      "code": "action_failed",
      "message": "API returned success=false"
    },
    {
      "user_id": 17411412,
      "status": 200,
      "code": "action_failed",
      "message": "API returned success=false"
    },
    {
      "user_id": 17413721,
      "status": 200,
      "code": "action_failed",
      "message": "API returned success=false"
    },
    {
      "user_id": 17455021,
      "status": 200,
      "code": "action_failed",
      "message": "API returned success=false"
    },
    {
      "user_id": 17476197,
      "status": 200,
      "code": "action_failed",
      "message": "API returned success=false"
    },
    {
      "user_id": 17481075,
      "status": 200,
      "code": "action_failed",
      "message": "API returned success=false"
    },
    {
      "user_id": 17592416,
      "status": 200,
      "code": "action_failed",
      "message": "API returned success=false"
    },
    {
      "user_id": 17678373,
      "status": 200,
      "code": "action_failed",
      "message": "API returned success=false"
    },
    {
      "user_id": 17678784,
      "status": 200,
      "code": "action_failed",
      "message": "API returned success=false"
    },
    {
      "user_id": 17720877,
      "status": 200,
      "code": "action_failed",
      "message": "API returned success=false"
    },
    {
      "user_id": 17733915,
      "status": 200,
      "code": "action_failed",
      "message": "API returned success=false"
    },
    {
      "user_id": 17792680,
      "status": 200,
      "code": "action_failed",
      "message": "API returned success=false"
    },
    {
      "user_id": 17795448,
      "status": 200,
      "code": "action_failed",
      "message": "API returned success=false"
    },
    {
      "user_id": 17854229,
      "status": 200,
      "code": "action_failed",
      "message": "API returned success=false"
    },
    {
      "user_id": 17865849,
      "status": 200,
      "code": "action_failed",
      "message": "API returned success=false"
    },
    {
      "user_id": 17869220,
      "status": 200,
      "code": "action_failed",
      "message": "API returned success=false"
    },
    {
      "user_id": 17871559,
      "status": 200,
      "code": "action_failed",
      "message": "API returned success=false"
    },
    {
      "user_id": 17882065,
      "status": 200,
      "code": "action_failed",
      "message": "API returned success=false"
    }
  ],
  "generated_at_iso": "2026-02-24T20:56:29.496Z"
}
