{
  "ok": true,
  "source_chat": {
    "chat_id": null,
    "title": null,
    "type": null,
    "status": null,
    "file": "пак1-11514.txt",
    "total_ids_in_source_file": 11513
  },
  "target_chat": {
    "chat_id": -73548651704408,
    "title": "Займы для всех",
    "type": "chat",
    "status": "active",
    "before_participants_count": 3663,
    "after_participants_count": 4489
  },
  "bot": {
    "user_id": 269932414,
    "name": "Интелликс",
    "username": "id613070470872_bot"
  },
  "bot_membership_in_target": {
    "status": 200,
    "data": {
      "members": [
        {
          "last_access_time": 0,
          "is_owner": false,
          "is_admin": true,
          "join_time": 1776519888854,
          "permissions": [
            "read_all_messages",
            "add_admins",
            "write",
            "change_chat_info",
            "add_remove_members",
            "can_call",
            "pin_message",
            "edit_link"
          ],
          "user_id": 269932414,
          "first_name": "Интелликс",
          "username": "id613070470872_bot",
          "is_bot": true,
          "last_activity_time": 1776524127468,
          "description": "Интелликс — умный чат-бот для быстрых ответов, идей и помощи в повседневных задачах.",
          "avatar_url": "https://i.oneme.ru/i?r=BTFjO43w8Yr1OSJ4tcurq5Hi8qZRFpjsW-cdEBxfPSRmW34BN_hBExMnnFcFEy-tCzo",
          "full_avatar_url": "https://i.oneme.ru/i?r=BTFjO43w8Yr1OSJ4tcurq5Hi40nY5-QvEnF9U6GjKypVHH4BN_hBExMnnFcFEy-tCzo",
          "name": "Интелликс"
        }
      ]
    }
  },
  "source_slice": {
    "start_index_0_based": 9756,
    "end_index_exclusive_0_based": 10756,
    "range_human": "9757-10756",
    "requested_count": 1000,
    "selected_count": 1000,
    "skipped_bot_self_count": 0,
    "processed_count": 1000,
    "invite_batch_size": 10
  },
  "run_options": {
    "dry_run": false,
    "invite_batch_size": 10,
    "pause_ms": 3000,
    "throttle_7m": false,
    "max_retries": 0,
    "retry_delay_ms": 1200,
    "retry_backoff": 2,
    "retry_action_failed": false,
    "split_action_failed_batch": false,
    "stop_on_consecutive_action_failed": 0,
    "skip_existing_scan": false,
    "verify_chunk_size": 100,
    "verify_pause_ms": 80
  },
  "precheck": {
    "target_snapshot_pages": 37,
    "target_snapshot_members_count": 3651
  },
  "stop_triggered": null,
  "already_in_target_count": 0,
  "attempted_invite_count": 1000,
  "invited_without_immediate_failure_count": 1000,
  "verified_added_count": 950,
  "still_not_in_target_from_attempted_count": 50,
  "not_attempted_due_to_stop_count": 0,
  "still_not_in_target_from_this_chunk_count": 50,
  "failed_by_code": {},
  "failed_by_status": {},
  "verification_errors_count": 0,
  "verification_errors_sample": [],
  "sample_verified_added_ids": [
    135537323,
    135864929,
    136142382,
    136445338,
    136768478,
    138081252,
    138082661,
    138195474,
    138344865,
    138556187,
    138584629,
    138685502,
    139042202,
    139185061,
    139240192,
    139564557,
    139565850,
    140262544,
    141837646,
    142108072,
    142416226,
    142555017,
    143163257,
    144157736,
    144450847,
    144731728,
    144776515,
    144887233,
    144942715,
    145539622,
    145811301,
    145833853,
    146166682,
    147803037,
    148287485,
    148400837,
    148517914,
    149296670,
    149873000,
    150448812,
    150747378,
    150852583,
    151030681,
    151064323,
    151265159,
    151820838,
    152563965,
    152602711,
    152755070,
    153586717
  ],
  "sample_still_missing_ids": [
    143431090,
    156446044,
    169230657,
    178012271,
    182482915,
    185136050,
    188231566,
    193422617,
    195385715,
    197260524,
    212065362,
    217828790,
    234849786,
    244912824,
    260127099,
    265240219,
    16785795,
    68678540,
    108375607,
    149295616,
    182931087,
    197547739,
    6693478,
    13303865,
    41747682,
    68187266,
    125170223,
    141680634,
    146927898,
    3024275,
    68545066,
    82222415,
    86647963,
    20482820,
    28192143,
    37260596,
    56282532,
    86656844,
    91761592,
    112566847,
    134367917,
    162524623,
    8857158,
    22544259,
    30325646,
    50570973,
    64977468,
    79549143,
    104206145,
    137349827
  ],
  "failed_details_sample": [],
  "generated_at_iso": "2026-04-18T15:01:13.226Z"
}
