{
  "ok": true,
  "source_chat": {
    "chat_id": null,
    "title": null,
    "type": null,
    "status": null,
    "file": "пак1-11514.txt",
    "total_ids_in_source_file": 11513
  },
  "target_chat": {
    "chat_id": -73543575285031,
    "title": "Деньги до зарплаты",
    "type": "chat",
    "status": "active",
    "before_participants_count": 1890,
    "after_participants_count": 2801
  },
  "bot": {
    "user_id": 269932414,
    "name": "Интелликс",
    "username": "id613070470872_bot"
  },
  "bot_membership_in_target": {
    "status": 200,
    "data": {
      "members": [
        {
          "last_access_time": 0,
          "is_owner": false,
          "is_admin": true,
          "join_time": 1776519847306,
          "permissions": [
            "read_all_messages",
            "add_remove_members",
            "pin_message",
            "can_call",
            "edit_link",
            "write",
            "add_admins",
            "change_chat_info"
          ],
          "user_id": 269932414,
          "first_name": "Интелликс",
          "username": "id613070470872_bot",
          "is_bot": true,
          "last_activity_time": 1776520874594,
          "description": "Интелликс — умный чат-бот для быстрых ответов, идей и помощи в повседневных задачах.",
          "avatar_url": "https://i.oneme.ru/i?r=BTFjO43w8Yr1OSJ4tcurq5Hi8qZRFpjsW-cdEBxfPSRmW34BN_hBExMnnFcFEy-tCzo",
          "full_avatar_url": "https://i.oneme.ru/i?r=BTFjO43w8Yr1OSJ4tcurq5Hi40nY5-QvEnF9U6GjKypVHH4BN_hBExMnnFcFEy-tCzo",
          "name": "Интелликс"
        }
      ]
    }
  },
  "source_slice": {
    "start_index_0_based": 2000,
    "end_index_exclusive_0_based": 3000,
    "range_human": "2001-3000",
    "requested_count": 1000,
    "selected_count": 1000,
    "skipped_bot_self_count": 0,
    "processed_count": 1000,
    "invite_batch_size": 10
  },
  "run_options": {
    "dry_run": false,
    "invite_batch_size": 10,
    "pause_ms": 3000,
    "throttle_7m": false,
    "max_retries": 0,
    "retry_delay_ms": 1200,
    "retry_backoff": 2,
    "retry_action_failed": false,
    "split_action_failed_batch": false,
    "stop_on_consecutive_action_failed": 0,
    "skip_existing_scan": false,
    "verify_chunk_size": 100,
    "verify_pause_ms": 80
  },
  "precheck": {
    "target_snapshot_pages": 19,
    "target_snapshot_members_count": 1890
  },
  "stop_triggered": null,
  "already_in_target_count": 0,
  "attempted_invite_count": 1000,
  "invited_without_immediate_failure_count": 1000,
  "verified_added_count": 960,
  "still_not_in_target_from_attempted_count": 40,
  "not_attempted_due_to_stop_count": 0,
  "still_not_in_target_from_this_chunk_count": 40,
  "failed_by_code": {},
  "failed_by_status": {},
  "verification_errors_count": 0,
  "verification_errors_sample": [],
  "sample_verified_added_ids": [
    138879116,
    139112606,
    140206245,
    140604855,
    140714278,
    141494345,
    141623777,
    142018914,
    142049080,
    142499776,
    143037644,
    143180884,
    143614754,
    144718914,
    145490544,
    145787480,
    146546878,
    146552334,
    146790269,
    147314689,
    149067646,
    149490514,
    149821485,
    151346912,
    151400822,
    153905135,
    154455448,
    154725594,
    154778329,
    155151432,
    155288121,
    155697315,
    156077163,
    156190590,
    157044989,
    157871903,
    159097392,
    160789774,
    161103906,
    161614837,
    162084734,
    166047180,
    166223375,
    166510190,
    167175676,
    168312107,
    169514267,
    169774522,
    170289127,
    171083686
  ],
  "sample_still_missing_ids": [
    139784085,
    183643730,
    207841077,
    232349411,
    13324549,
    18697331,
    18892538,
    36751906,
    44178968,
    67958703,
    114510031,
    138270528,
    149501877,
    150928936,
    170993526,
    220147726,
    235251548,
    241713575,
    16352004,
    20338114,
    52448328,
    106609525,
    120484831,
    152650831,
    160673469,
    181175002,
    189780502,
    198103217,
    6985103,
    13382725,
    16148789,
    17164257,
    20928093,
    30862077,
    35230739,
    37725689,
    43200526,
    54806941,
    79262542,
    117699471
  ],
  "failed_details_sample": [],
  "generated_at_iso": "2026-04-18T14:06:59.351Z"
}
