{
  "ok": true,
  "source_chat": {
    "chat_id": null,
    "title": null,
    "type": null,
    "status": null,
    "file": "data/eysk_all_chats_except_eysk_obyavleniya_novosti_member_ids_no_bots_no_admins_20260227004122.json",
    "total_ids_in_source_file": 2666
  },
  "target_chat": {
    "chat_id": -71489737820167,
    "title": "Ейск Объявления | Новости",
    "type": "chat",
    "status": "active",
    "before_participants_count": 290,
    "after_participants_count": 623
  },
  "bot": {
    "user_id": 213352639,
    "name": "Чат Помощник",
    "username": "id613002203036_3_bot"
  },
  "bot_membership_in_target": {
    "status": 200,
    "data": {
      "members": [
        {
          "last_access_time": 0,
          "is_owner": false,
          "is_admin": true,
          "join_time": 1772140307172,
          "permissions": [
            "pin_message",
            "write",
            "read_all_messages",
            "change_chat_info",
            "add_remove_members",
            "can_call"
          ],
          "user_id": 213352639,
          "first_name": "Чат Помощник",
          "username": "id613002203036_3_bot",
          "is_bot": true,
          "last_activity_time": 1772142284274,
          "description": "Бот Менеджер — инструмент для работы в чатах и каналах: модерация, автоответы, публикация постов, сбор заявок и управление участниками. Упрощает администрирование и экономит время 24/7.",
          "avatar_url": "https://i.oneme.ru/i?r=BTFjO43w8Yr1OSJ4tcurq5Hi_NR_nlJAbr9fifLd9y_xML1fUr_RplD5k9xqRaiD8lo",
          "full_avatar_url": "https://i.oneme.ru/i?r=BTFjO43w8Yr1OSJ4tcurq5HiCPJhPxK6VFVM3kbkFPAU7b1fUr_RplD5k9xqRaiD8lo",
          "name": "Чат Помощник"
        }
      ]
    }
  },
  "source_slice": {
    "start_index_0_based": 400,
    "end_index_exclusive_0_based": 800,
    "range_human": "401-800",
    "requested_count": 400,
    "selected_count": 400,
    "skipped_bot_self_count": 0,
    "processed_count": 400,
    "invite_batch_size": 10
  },
  "run_options": {
    "dry_run": false,
    "invite_batch_size": 10,
    "pause_ms": 180,
    "max_retries": 1,
    "retry_delay_ms": 1200,
    "retry_backoff": 2,
    "retry_action_failed": false,
    "split_action_failed_batch": false,
    "stop_on_consecutive_action_failed": 2,
    "skip_existing_scan": false,
    "verify_chunk_size": 100,
    "verify_pause_ms": 80
  },
  "precheck": {
    "target_snapshot_pages": 3,
    "target_snapshot_members_count": 290
  },
  "stop_triggered": null,
  "already_in_target_count": 0,
  "attempted_invite_count": 400,
  "invited_without_immediate_failure_count": 400,
  "verified_added_count": 333,
  "still_not_in_target_from_attempted_count": 67,
  "not_attempted_due_to_stop_count": 0,
  "still_not_in_target_from_this_chunk_count": 67,
  "failed_by_code": {},
  "failed_by_status": {},
  "verification_errors_count": 0,
  "verification_errors_sample": [],
  "sample_verified_added_ids": [
    25544018,
    25544253,
    25550913,
    25599176,
    25607608,
    25645731,
    25716032,
    25729960,
    25777896,
    25930986,
    25935867,
    25944203,
    25945106,
    26032515,
    26037269,
    26049398,
    26059922,
    26063749,
    26063828,
    26103205,
    26113799,
    26120487,
    26160689,
    26199465,
    26220398,
    26297243,
    26315172,
    26315559,
    26341045,
    26407106,
    26524678,
    26574317,
    26731531,
    26776130,
    26778352,
    26784983,
    26883784,
    26898812,
    27021108,
    27050458,
    27054412,
    27066542,
    27117446,
    27120428,
    27131042,
    27262492,
    27332423,
    27383210,
    27386035,
    27491231
  ],
  "sample_still_missing_ids": [
    25600815,
    25756898,
    25814726,
    25824207,
    25878668,
    26132443,
    26156035,
    26183810,
    26215981,
    26571096,
    26776184,
    26943626,
    27165265,
    27167978,
    27220959,
    27325491,
    27343014,
    27588867,
    27604664,
    27782229,
    28299862,
    28414274,
    28591411,
    29185985,
    29659086,
    30070589,
    30475077,
    31205016,
    31317810,
    31443726,
    31451303,
    31490663,
    31745861,
    31916239,
    32094920,
    32608511,
    32721611,
    32880220,
    33589701,
    34075104,
    34401250,
    34916005,
    35175456,
    35236717,
    35289040,
    35923523,
    35927165,
    36024687,
    37618523,
    37705109
  ],
  "failed_details_sample": [],
  "generated_at_iso": "2026-02-26T21:45:09.033Z"
}
