{
  "generated_at": "2026-03-10T17:44:24.190Z",
  "city": "tyumen",
  "source": "live_by_current_bot_token",
  "matching_rule": "/(^|[^а-яёa-z])(тюмень|тюменская\\s+область|tyumen)([^а-яёa-z]|$)/iu",
  "total_visible_chats": 362,
  "get_all_chats_pages": 4,
  "matched_chats_including_target_count": 10,
  "source_chats_count": 9,
  "source_chats": [
    {
      "chat_id": -71545139983730,
      "title": "Тюмень для своих",
      "type": "chat",
      "status": "active",
      "participants_count": 490,
      "link": "https://max.ru/join/fvXj6DNiXJeboc5cmEvogFoGe46rZcw4twa29uk16_s"
    },
    {
      "chat_id": -68233959814571,
      "title": "🪧 ОБЪЯВЛЕНИЯ-ТЮМЕНЬ! 🏡ТЮМЕНСКАЯ ОБЛАСТЬ! 💬",
      "type": "chat",
      "status": "active",
      "participants_count": 623,
      "link": "https://max.ru/join/IDlYzU9RKSs44gz_HYDrpaBLC1LO7DeW6MQGsZzIsIo"
    },
    {
      "chat_id": -70946379893481,
      "title": "Район Ватутина ММС Парфеново Тюмень",
      "type": "chat",
      "status": "active",
      "participants_count": 338,
      "link": "https://max.ru/join/3m1O8IUuSnbWE06OqNb7_w39-6ysDJcxLv_4gE1tIuk"
    },
    {
      "chat_id": -69574891847771,
      "title": "ТЮМЕНЬ ОБЬЯВЛЕНИЯ",
      "type": "chat",
      "status": "active",
      "participants_count": 390,
      "link": "https://max.ru/join/nTSfGFBYPVeCre8vh5ryOVMuBO_ywp78m2WIhJttdkA"
    },
    {
      "chat_id": -71295370889742,
      "title": "ТЮМЕНЬ • ОБЪЯВЛЕНИЯ",
      "type": "chat",
      "status": "active",
      "participants_count": 2159,
      "link": "https://max.ru/join/fdqUX6StomhlJpjZCc8Xe7fzQiHjaNPq9BGeCpuHWmQ"
    },
    {
      "chat_id": -69538142025203,
      "title": "Работа, подработка Тюмень",
      "type": "chat",
      "status": "active",
      "participants_count": 2448,
      "link": "https://max.ru/join/VkU9KQW68IFajqiw0iTqv3jmgwgWm4qTPsgQGDqNBOY"
    },
    {
      "chat_id": -71408558423353,
      "title": "Тюменская Слобода. Тюмень. Продам/куплю. Объявления. Реклама.",
      "type": "chat",
      "status": "active",
      "participants_count": 157,
      "link": "https://max.ru/join/Ded6C8wGBeDGRTkUGRuamnGH90DoBjjg9jJT9b-a4WM"
    },
    {
      "chat_id": -71790205733384,
      "title": "Apple барахолка Тюмень",
      "type": "chat",
      "status": "active",
      "participants_count": 589,
      "link": "https://max.ru/join/jChMrX5rPhuTF7mNv8eA5Zdny8BBD658AS0JipteV2E"
    },
    {
      "chat_id": -71745026984456,
      "title": "Авторынок Тюмень",
      "type": "chat",
      "status": "active",
      "participants_count": 409,
      "link": "https://max.ru/join/Zcku8u5THgOln15_PtM4KJEEJXkf2n1m3azqXG2E6bs"
    }
  ],
  "target_chat": {
    "chat_id": -71520449562631,
    "title": "Тюмень Объявления | Новости",
    "type": "chat",
    "status": "active",
    "participants_count": 2604,
    "link": null
  },
  "target_members_snapshot": {
    "members_count": 2598,
    "pages": 26
  },
  "unique_ids_count": 2852,
  "per_chat": [
    {
      "chat_id": -71545139983730,
      "title": "Тюмень для своих",
      "type": "chat",
      "status": "active",
      "participants_count": 490,
      "pages": 5,
      "members_fetched": 490,
      "skipped_bots": 1,
      "skipped_admins": 2,
      "skipped_invalid": 0,
      "kept_non_bot_non_admin": 487,
      "skipped_already_in_target": 50,
      "unique_new_from_chat": 437,
      "link": "https://max.ru/join/fvXj6DNiXJeboc5cmEvogFoGe46rZcw4twa29uk16_s"
    },
    {
      "chat_id": -68233959814571,
      "title": "🪧 ОБЪЯВЛЕНИЯ-ТЮМЕНЬ! 🏡ТЮМЕНСКАЯ ОБЛАСТЬ! 💬",
      "type": "chat",
      "status": "active",
      "participants_count": 623,
      "pages": 7,
      "members_fetched": 623,
      "skipped_bots": 1,
      "skipped_admins": 1,
      "skipped_invalid": 0,
      "kept_non_bot_non_admin": 621,
      "skipped_already_in_target": 290,
      "unique_new_from_chat": 292,
      "link": "https://max.ru/join/IDlYzU9RKSs44gz_HYDrpaBLC1LO7DeW6MQGsZzIsIo"
    },
    {
      "chat_id": -70946379893481,
      "title": "Район Ватутина ММС Парфеново Тюмень",
      "type": "chat",
      "status": "active",
      "participants_count": 338,
      "pages": 4,
      "members_fetched": 338,
      "skipped_bots": 7,
      "skipped_admins": 2,
      "skipped_invalid": 0,
      "kept_non_bot_non_admin": 329,
      "skipped_already_in_target": 123,
      "unique_new_from_chat": 147,
      "link": "https://max.ru/join/3m1O8IUuSnbWE06OqNb7_w39-6ysDJcxLv_4gE1tIuk"
    },
    {
      "chat_id": -69574891847771,
      "title": "ТЮМЕНЬ ОБЬЯВЛЕНИЯ",
      "type": "chat",
      "status": "active",
      "participants_count": 390,
      "pages": 4,
      "members_fetched": 390,
      "skipped_bots": 2,
      "skipped_admins": 2,
      "skipped_invalid": 0,
      "kept_non_bot_non_admin": 386,
      "skipped_already_in_target": 191,
      "unique_new_from_chat": 111,
      "link": "https://max.ru/join/nTSfGFBYPVeCre8vh5ryOVMuBO_ywp78m2WIhJttdkA"
    },
    {
      "chat_id": -71295370889742,
      "title": "ТЮМЕНЬ • ОБЪЯВЛЕНИЯ",
      "type": "chat",
      "status": "active",
      "participants_count": 2159,
      "pages": 22,
      "members_fetched": 2159,
      "skipped_bots": 1,
      "skipped_admins": 2,
      "skipped_invalid": 0,
      "kept_non_bot_non_admin": 2156,
      "skipped_already_in_target": 1286,
      "unique_new_from_chat": 772,
      "link": "https://max.ru/join/fdqUX6StomhlJpjZCc8Xe7fzQiHjaNPq9BGeCpuHWmQ"
    },
    {
      "chat_id": -69538142025203,
      "title": "Работа, подработка Тюмень",
      "type": "chat",
      "status": "active",
      "participants_count": 2448,
      "pages": 25,
      "members_fetched": 2448,
      "skipped_bots": 1,
      "skipped_admins": 4,
      "skipped_invalid": 0,
      "kept_non_bot_non_admin": 2443,
      "skipped_already_in_target": 1154,
      "unique_new_from_chat": 1012,
      "link": "https://max.ru/join/VkU9KQW68IFajqiw0iTqv3jmgwgWm4qTPsgQGDqNBOY"
    },
    {
      "chat_id": -71408558423353,
      "title": "Тюменская Слобода. Тюмень. Продам/куплю. Объявления. Реклама.",
      "type": "chat",
      "status": "active",
      "participants_count": 157,
      "pages": 2,
      "members_fetched": 157,
      "skipped_bots": 1,
      "skipped_admins": 2,
      "skipped_invalid": 0,
      "kept_non_bot_non_admin": 154,
      "skipped_already_in_target": 44,
      "unique_new_from_chat": 58,
      "link": "https://max.ru/join/Ded6C8wGBeDGRTkUGRuamnGH90DoBjjg9jJT9b-a4WM"
    },
    {
      "chat_id": -71790205733384,
      "title": "Apple барахолка Тюмень",
      "type": "chat",
      "status": "active",
      "participants_count": 589,
      "pages": 6,
      "members_fetched": 589,
      "skipped_bots": 1,
      "skipped_admins": 1,
      "skipped_invalid": 0,
      "kept_non_bot_non_admin": 587,
      "skipped_already_in_target": 388,
      "unique_new_from_chat": 9,
      "link": "https://max.ru/join/jChMrX5rPhuTF7mNv8eA5Zdny8BBD658AS0JipteV2E"
    },
    {
      "chat_id": -71745026984456,
      "title": "Авторынок Тюмень",
      "type": "chat",
      "status": "active",
      "participants_count": 409,
      "pages": 5,
      "members_fetched": 409,
      "skipped_bots": 1,
      "skipped_admins": 2,
      "skipped_invalid": 0,
      "kept_non_bot_non_admin": 406,
      "skipped_already_in_target": 275,
      "unique_new_from_chat": 14,
      "link": "https://max.ru/join/Zcku8u5THgOln15_PtM4KJEEJXkf2n1m3azqXG2E6bs"
    }
  ],
  "result_file_txt": "data/tyumen_all_other_visible_chats_member_ids_no_bots_no_admins_not_in_target_live_20260310_204424.txt",
  "result_file_json": "data/tyumen_all_other_visible_chats_member_ids_no_bots_no_admins_not_in_target_live_20260310_204424.json"
}
